glance/__init__.py
glance/context.py
glance/gateway.py
glance/housekeeping.py
glance/i18n.py
glance/location.py
glance/notifier.py
glance/opts.py
glance/schema.py
glance/scrubber.py
glance/sqlite_migration.py
glance/task_cancellation_tracker.py
glance/version.py
glance/api/__init__.py
glance/api/common.py
glance/api/policy.py
glance/api/property_protections.py
glance/api/versions.py
glance/api/middleware/__init__.py
glance/api/middleware/cache.py
glance/api/middleware/cache_manage.py
glance/api/middleware/context.py
glance/api/middleware/gzip.py
glance/api/middleware/version_negotiation.py
glance/api/v1/__init__.py
glance/api/v1/router.py
glance/api/v2/__init__.py
glance/api/v2/cached_images.py
glance/api/v2/discovery.py
glance/api/v2/image_actions.py
glance/api/v2/image_data.py
glance/api/v2/image_members.py
glance/api/v2/image_tags.py
glance/api/v2/images.py
glance/api/v2/metadef_namespaces.py
glance/api/v2/metadef_objects.py
glance/api/v2/metadef_properties.py
glance/api/v2/metadef_resource_types.py
glance/api/v2/metadef_tags.py
glance/api/v2/policy.py
glance/api/v2/router.py
glance/api/v2/schemas.py
glance/api/v2/tasks.py
glance/api/v2/model/__init__.py
glance/api/v2/model/metadef_namespace.py
glance/api/v2/model/metadef_object.py
glance/api/v2/model/metadef_property_item_type.py
glance/api/v2/model/metadef_property_type.py
glance/api/v2/model/metadef_resource_type.py
glance/api/v2/model/metadef_tag.py
glance/async_/__init__.py
glance/async_/taskflow_executor.py
glance/async_/utils.py
glance/async_/flows/__init__.py
glance/async_/flows/api_image_import.py
glance/async_/flows/base_import.py
glance/async_/flows/convert.py
glance/async_/flows/introspect.py
glance/async_/flows/location_import.py
glance/async_/flows/ovf_process.py
glance/async_/flows/_internal_plugins/__init__.py
glance/async_/flows/_internal_plugins/base_download.py
glance/async_/flows/_internal_plugins/copy_image.py
glance/async_/flows/_internal_plugins/glance_download.py
glance-31.0.0.dist-info/AUTHORS
glance-31.0.0.dist-info/LICENSE
glance-31.0.0.dist-info/METADATA
glance-31.0.0.dist-info/WHEEL
glance-31.0.0.dist-info/entry_points.txt
glance-31.0.0.dist-info/pbr.json
glance-31.0.0.dist-info/top_level.txt
glance-31.0.0.dist-info/RECORD
