Metadata-Version: 2.1
Name: glance
Version: 31.0.0
Summary: OpenStack Image Service
Home-page: https://docs.openstack.org/glance/latest/
Author: OpenStack
Author-email: openstack-discuss@lists.openstack.org
Classifier: Environment :: OpenStack
Classifier: Intended Audience :: Information Technology
Classifier: Intended Audience :: System Administrators
Classifier: License :: OSI Approved :: Apache Software License
Classifier: Operating System :: POSIX :: Linux
Classifier: Programming Language :: Python
Classifier: Programming Language :: Python :: 3 :: Only
Classifier: Programming Language :: Python :: 3
Classifier: Programming Language :: Python :: 3.10
Classifier: Programming Language :: Python :: 3.11
Classifier: Programming Language :: Python :: 3.12
Requires-Python: >=3.10
License-File: LICENSE
License-File: AUTHORS
Requires-Dist: pbr >=3.1.1
Requires-Dist: defusedxml >=0.7.1
Requires-Dist: SQLAlchemy >=1.3.14
Requires-Dist: eventlet >=0.33.3
Requires-Dist: PasteDeploy >=1.5.0
Requires-Dist: Routes >=2.3.1
Requires-Dist: WebOb >=1.8.1
Requires-Dist: alembic >=0.9.6
Requires-Dist: httplib2 >=0.9.1
Requires-Dist: oslo.config >=8.1.0
Requires-Dist: oslo.concurrency >=4.5.1
Requires-Dist: oslo.context >=2.22.0
Requires-Dist: oslo.upgradecheck >=1.3.0
Requires-Dist: oslo.utils >=7.3.0
Requires-Dist: stevedore !=3.0.0,>=1.20.0
Requires-Dist: futurist >=1.2.0
Requires-Dist: taskflow >=4.0.0
Requires-Dist: keystoneauth1 >=3.4.0
Requires-Dist: keystonemiddleware >=5.1.0
Requires-Dist: WSME >=0.8.0
Requires-Dist: PrettyTable >=0.7.1
Requires-Dist: Paste >=2.0.2
Requires-Dist: jsonschema >=3.2.0
Requires-Dist: python-keystoneclient >=3.8.0
Requires-Dist: oslo.db >=5.0.0
Requires-Dist: oslo.i18n >=5.0.0
Requires-Dist: oslo.limit >=1.6.0
Requires-Dist: oslo.log >=4.5.0
Requires-Dist: oslo.messaging !=9.0.0,>=5.29.0
Requires-Dist: oslo.middleware >=3.31.0
Requires-Dist: oslo.reports >=1.18.0
Requires-Dist: oslo.policy >=4.5.0
Requires-Dist: retrying !=1.3.0,>=1.2.3
Requires-Dist: osprofiler >=1.4.0
Requires-Dist: glance-store >=4.9.0
Requires-Dist: debtcollector >=1.19.0
Requires-Dist: cryptography >=2.6.1
Requires-Dist: cursive >=0.2.1
Requires-Dist: castellan >=0.17.0
